{
  "content" : {
    "elements" : [
      {
        "elements" : [
          {
            "elements" : [
              {
                "options" : {
                  "label" : "#lang/abbreviation"
                },
                "scope" : "#/properties/abbreviation",
                "type" : "Control"
              },
              {
                "options" : {
                  "label" : "#lang/name"
                },
                "scope" : "#/properties/name",
                "type" : "Control"
              }
            ],
            "options" : {
              "direction" : "horizontal",
              "format" : "group"
            },
            "type" : "Layout"
          },
          {
            "options" : {
              "format" : "multiline",
              "label" : "#lang/description"
            },
            "scope" : "#/properties/description",
            "type" : "Control"
          },
          {
            "options" : {
              "label" : "#lang/scenario_generalInformation_document"
            },
            "scope" : "#/properties/customAspects/properties/scenario_generalInformation/properties/attributes/properties/scenario_generalInformation_document",
            "type" : "Control"
          }
        ],
        "options" : {
          "format" : "group",
          "label" : "#lang/group_a44fc0d1-6c87-41cf-989e-f031d3f52b44"
        },
        "type" : "Layout"
      },
      {
        "elements" : [
          {
            "options" : {
              "format" : "autocomplete",
              "label" : "#lang/scenario_vulnerability_type"
            },
            "scope" : "#/properties/customAspects/properties/scenario_vulnerability/properties/attributes/properties/scenario_vulnerability_type",
            "type" : "Control"
          },
          {
            "options" : {
              "label" : "#lang/scenario_vulnerability_otherType"
            },
            "rule" : {
              "condition" : {
                "schema" : {
                  "enum" : [
                    "scenario_vulnerability_type_other"
                  ]
                },
                "scope" : "#/properties/customAspects/properties/scenario_vulnerability/properties/attributes/properties/scenario_vulnerability_type"
              },
              "effect" : "SHOW"
            },
            "scope" : "#/properties/customAspects/properties/scenario_vulnerability/properties/attributes/properties/scenario_vulnerability_otherType",
            "type" : "Control"
          }
        ],
        "options" : {
          "format" : "group",
          "label" : "#lang/group_b29f2d5a-ff36-4a0f-96c5-ece8d91c621d"
        },
        "type" : "Layout"
      },
      {
        "elements" : [
          {
            "options" : {
              "format" : "autocomplete",
              "label" : "#lang/scenario_threat_type"
            },
            "scope" : "#/properties/customAspects/properties/scenario_threat/properties/attributes/properties/scenario_threat_type",
            "type" : "Control"
          },
          {
            "options" : {
              "label" : "#lang/scenario_threat_otherType"
            },
            "rule" : {
              "condition" : {
                "schema" : {
                  "enum" : [
                    "scenario_threat_type_other"
                  ]
                },
                "scope" : "#/properties/customAspects/properties/scenario_threat/properties/attributes/properties/scenario_threat_type"
              },
              "effect" : "SHOW"
            },
            "scope" : "#/properties/customAspects/properties/scenario_threat/properties/attributes/properties/scenario_threat_otherType",
            "type" : "Control"
          }
        ],
        "options" : {
          "format" : "group",
          "label" : "#lang/group_0c6f4c1f-57fa-41e6-a2e4-4695a772e69c"
        },
        "type" : "Layout"
      }
    ],
    "options" : {
      "direction" : "vertical",
      "format" : "group"
    },
    "type" : "Layout"
  },
  "modelType" : "scenario",
  "name" : {
    "de" : "Gefährdung",
    "en" : "Scenario"
  },
  "subType" : "SCN_Scenario",
  "translation" : {
    "de" : {
      "group_0c6f4c1f-57fa-41e6-a2e4-4695a772e69c" : "Bedrohung",
      "group_a44fc0d1-6c87-41cf-989e-f031d3f52b44" : "Allgemeine Angaben",
      "group_b29f2d5a-ff36-4a0f-96c5-ece8d91c621d" : "Schwachstelle"
    },
    "en" : {
      "group_0c6f4c1f-57fa-41e6-a2e4-4695a772e69c" : "Threat",
      "group_a44fc0d1-6c87-41cf-989e-f031d3f52b44" : "General Information",
      "group_b29f2d5a-ff36-4a0f-96c5-ece8d91c621d" : "Vulnerability"
    }
  }
}